MANIFEST.in
README.rst
manual.html
setup.py
libleipzig/__init__.py
libleipzig/main.py
libleipzig/protocol.py
libleipzig/transport.py
libleipzig.egg-info/PKG-INFO
libleipzig.egg-info/SOURCES.txt
libleipzig.egg-info/dependency_links.txt
libleipzig.egg-info/entry_points.txt
libleipzig.egg-info/requires.txt
libleipzig.egg-info/top_level.txt
libleipzig.egg-info/zip-safe
tests/__init__.py
tests/test_data.py
tests/test_interface.py
tests/test_service.py