Metadata-Version: 1.0
Name: libleipzig
Version: 1.3
Summary: wortschatz.uni-leipzig.de binding
Home-page: http://github.com/lehmannro/libleipzig-python/
Author: Robert Lehmann
Author-email: libleipzig@robertlehmann.de
License: GPLv3
Platform: UNKNOWN
Classifier: Environment :: Web Environment
Classifier: License :: OSI Approved :: GNU General Public License (GPL)
Classifier: Natural Language :: German
Classifier: Topic :: Text Processing :: Linguistic
